simple_work_queue/__init__.py
simple_work_queue/queue_consumer.py
simple_work_queue/queue_publisher.py
simple_work_queue-0.1.5.dist-info/LICENSE.txt
simple_work_queue-0.1.5.dist-info/METADATA
simple_work_queue-0.1.5.dist-info/WHEEL
simple_work_queue-0.1.5.dist-info/RECORD
